dssm_python/__init__.py
dssm_python/libssm.py
dssm_python/libssm_shm.py
dssm_python/libssm_time.py
dssm_python/ssm.py
dssm_python-0.0.3.dist-info/METADATA
dssm_python-0.0.3.dist-info/WHEEL
dssm_python-0.0.3.dist-info/licenses/LICENSE
dssm_python-0.0.3.dist-info/RECORD
