Metadata-Version: 2.4
Name: dssm_python
Version: 0.0.3
Summary: Python interface for DSSM
Project-URL: Homepage, https://github.com/DSSS-Lab/dssm-python.git
Project-URL: Issues, https://github.com/DSSS-Lab/dssm-python/issues
Author-email: Louis Schraeder <z524037@shibaura-it.ac.jp>, Hiroaki Fukuda <hiroaki@shibaura-it.ac.jp>
License-File: LICENSE
Classifier: License :: OSI Approved :: MIT License
Classifier: Operating System :: MacOS
Classifier: Operating System :: POSIX :: Linux
Classifier: Programming Language :: Python :: 3
Requires-Python: >=3.8
Requires-Dist: sysv-ipc
